int.py
setup.py
int.egg-info/PKG-INFO
int.egg-info/SOURCES.txt
int.egg-info/dependency_links.txt
int.egg-info/entry_points.txt
int.egg-info/top_level.txt