Metadata-Version: 1.1
Name: int
Version: 2.1.0
Summary: Integer conversion utility.
Home-page: https://github.com/dmulholland/int
Author: Darren Mulholland
Author-email: UNKNOWN
License: Public Domain
Platform: UNKNOWN
Classifier: Development Status :: 5 - Production/Stable
Classifier: Programming Language :: Python :: 3
Classifier: Operating System :: OS Independent
Classifier: License :: Public Domain
Classifier: Topic :: Utilities
